test/sdk-test.py
watcher/__init__.py
watcher/main.py
watcher/sdk.py
watcher_interpreter-0.0.1.dist-info/LICENSE
watcher_interpreter-0.0.1.dist-info/METADATA
watcher_interpreter-0.0.1.dist-info/WHEEL
watcher_interpreter-0.0.1.dist-info/entry_points.txt
watcher_interpreter-0.0.1.dist-info/top_level.txt
watcher_interpreter-0.0.1.dist-info/RECORD
