Metadata-Version: 2.1
Name: watcher-interpreter
Version: 0.0.1
Summary: Running interpreter with watcher in command
Author-email: luozhixin <zhixin.luo@seeed.cc>
Project-URL: Homepage, https://github.com/Seeed-Projects/watcher-interpreter
Project-URL: Issues, https://github.com/Seeed-Projects/watcher-interpreter/issues
Keywords: watcher,seeed,llm
Classifier: Programming Language :: Python :: 3
Classifier: License :: OSI Approved :: MIT License
Classifier: Operating System :: OS Independent
Requires-Python: >=3.8
License-File: LICENSE
